xcytxs_setup/__init__.py
xcytxs_setup-0.1.dist-info/LICENSE
xcytxs_setup-0.1.dist-info/METADATA
xcytxs_setup-0.1.dist-info/WHEEL
xcytxs_setup-0.1.dist-info/entry_points.txt
xcytxs_setup-0.1.dist-info/top_level.txt
xcytxs_setup-0.1.dist-info/RECORD
