Metadata-Version: 2.1
Name: xcytxs-setup
Version: 0.1
Summary: An automated setup tool for configuring services and installing dependencies.
Home-page: https://github.com/xcytxs/setup
Author: xcyt
Author-email: xcytdev@gmail.com
Classifier: Programming Language :: Python :: 3
Classifier: License :: OSI Approved :: GNU General Public License v3 (GPLv3)
Classifier: Operating System :: OS Independent
Requires-Python: >=3.6
License-File: LICENSE
Requires-Dist: pip
